giskardpy_bullet_bindings/__init__.py
giskardpy_bullet_bindings/_giskardpy_bullet_bindings.cpython-311-x86_64-linux-gnu.so
giskardpy_bullet_bindings/include/ActiveSocket.h
giskardpy_bullet_bindings/include/Host.h
giskardpy_bullet_bindings/include/PassiveSocket.h
giskardpy_bullet_bindings/include/SimpleSocket.h
giskardpy_bullet_bindings/include/StatTimer.h
giskardpy_bullet_bindings/include/bullet/btBulletCollisionCommon.h
giskardpy_bullet_bindings/include/bullet/btBulletDynamicsCommon.h
giskardpy_bullet_bindings/include/bullet/BasicDemo/BasicExample.h
giskardpy_bullet_bindings/include/bullet/Benchmarks/BenchmarkDemo.h
giskardpy_bullet_bindings/include/bullet/Benchmarks/HaltonData.h
giskardpy_bullet_bindings/include/bullet/Benchmarks/TaruData.h
giskardpy_bullet_bindings/include/bullet/Benchmarks/landscapeData.h
giskardpy_bullet_bindings/include/bullet/Bullet2FileLoader/b3BulletFile.h
giskardpy_bullet_bindings/include/bullet/Bullet2FileLoader/b3Chunk.h
giskardpy_bullet_bindings/include/bullet/Bullet2FileLoader/b3Common.h
giskardpy_bullet_bindings/include/bullet/Bullet2FileLoader/b3DNA.h
giskardpy_bullet_bindings/include/bullet/Bullet2FileLoader/b3Defines.h
giskardpy_bullet_bindings/include/bullet/Bullet2FileLoader/b3File.h
giskardpy_bullet_bindings/include/bullet/Bullet2FileLoader/b3Serializer.h
giskardpy_bullet_bindings/include/bullet/Bullet2FileLoader/autogenerated/bullet2.h
giskardpy_bullet_bindings/include/bullet/Bullet3Collision/BroadPhaseCollision/b3BroadphaseCallback.h
giskardpy_bullet_bindings/include/bullet/Bullet3Collision/BroadPhaseCollision/b3DynamicBvh.h
giskardpy_bullet_bindings/include/bullet/Bullet3Collision/BroadPhaseCollision/b3DynamicBvhBroadphase.h
giskardpy_bullet_bindings/include/bullet/Bullet3Collision/BroadPhaseCollision/b3OverlappingPair.h
giskardpy_bullet_bindings/include/bullet/Bullet3Collision/BroadPhaseCollision/b3OverlappingPairCache.h
giskardpy_bullet_bindings-1.0.1.dist-info/METADATA
giskardpy_bullet_bindings-1.0.1.dist-info/WHEEL
giskardpy_bullet_bindings-1.0.1.dist-info/top_level.txt
giskardpy_bullet_bindings-1.0.1.dist-info/RECORD
giskardpy_bullet_bindings-1.0.1.dist-info/licenses/AUTHORS.txt
giskardpy_bullet_bindings-1.0.1.dist-info/licenses/LICENSE.txt
