Metadata-Version: 2.1
Name: giskardpy_bullet_bindings
Version: 1.0.1
Summary: Custom bullet wrapper used by Giskardpy
Home-page: https://github.com/SemRoCo/bullet3
Author: Simon Stelter
License: zlib
Keywords: physics simulation,robotics,collision detection,opengl
Platform: any
Classifier: Operating System :: POSIX :: Linux
Classifier: Programming Language :: Python :: 3.8
Classifier: Programming Language :: Python :: 3.9
Classifier: Programming Language :: Python :: 3.10
Classifier: Programming Language :: Python :: 3.11
Classifier: Programming Language :: Python :: 3.12
Classifier: Topic :: Scientific/Engineering :: Artificial Intelligence
Classifier: Topic :: Games/Entertainment :: Simulation
Classifier: Framework :: Robot Framework
License-File: LICENSE.txt
License-File: AUTHORS.txt
